spidermon/VERSION
spidermon/__init__.py
spidermon/data.py
spidermon/exceptions.py
spidermon/loaders.py
spidermon/runners.py
spidermon/settings.py
spidermon/templates.py
spidermon/contrib/__init__.py
spidermon/contrib/actions/__init__.py
spidermon/contrib/actions/templates.py
spidermon/contrib/actions/discord/__init__.py
spidermon/contrib/actions/discord/notifiers.py
spidermon/contrib/actions/discord/templates/discord/default/message.jinja
spidermon/contrib/actions/discord/templates/discord/spider/notifier/macros.jinja
spidermon/contrib/actions/discord/templates/discord/spider/notifier/finish/message.jinja
spidermon/contrib/actions/discord/templates/discord/spider/notifier/periodic/message.jinja
spidermon/contrib/actions/discord/templates/discord/spider/notifier/start/message.jinja
spidermon/contrib/actions/email/__init__.py
spidermon/contrib/actions/email/ses.py
spidermon/contrib/actions/email/smtp.py
spidermon/contrib/actions/jobs/__init__.py
spidermon/contrib/actions/jobs/tags.py
spidermon/contrib/actions/reports/__init__.py
spidermon/contrib/actions/reports/files.py
spidermon/contrib/actions/reports/s3.py
spidermon/contrib/actions/reports/templates/reports/email/bases/report/base.jinja
spidermon/contrib/actions/reports/templates/reports/email/bases/report/big.jinja
spidermon/contrib/actions/reports/templates/reports/email/bases/report/email.css
spidermon/contrib/actions/reports/templates/reports/email/bases/report/medium.jinja
spidermon/contrib/actions/reports/templates/reports/email/bases/report/report.css
spidermon/contrib/actions/reports/templates/reports/email/bases/report/small.jinja
spidermon/contrib/actions/reports/templates/reports/email/monitors/result.css
spidermon/contrib/actions/reports/templates/reports/email/monitors/result.jinja
spidermon/contrib/actions/sentry/__init__.py
spidermon/contrib/actions/slack/__init__.py
spidermon/contrib/actions/slack/notifiers.py
spidermon/contrib/actions/slack/templates/slack/default/attachments.jinja
spidermon-1.24.0.dist-info/licenses/LICENSE
spidermon-1.24.0.dist-info/METADATA
spidermon-1.24.0.dist-info/WHEEL
spidermon-1.24.0.dist-info/top_level.txt
spidermon-1.24.0.dist-info/RECORD
