Metadata-Version: 2.4
Name: spidermon
Version: 1.24.0
Summary: Spidermon is a framework to build monitors for Scrapy spiders.
Home-page: https://github.com/scrapinghub/spidermon
Author: Zyte
Author-email: opensource@zyte.com
License: BSD
Project-URL: Documentation, https://spidermon.readthedocs.io/
Project-URL: Source, https://github.com/scrapinghub/spidermon
Project-URL: Tracker, https://github.com/scrapinghub/spidermon/issues
Project-URL: Release notes, https://spidermon.readthedocs.io/en/latest/changelog.html
Classifier: Development Status :: 5 - Production/Stable
Classifier: Framework :: Scrapy
Classifier: Intended Audience :: Developers
Classifier: License :: OSI Approved :: BSD License
Classifier: Operating System :: OS Independent
Classifier: Programming Language :: Python
Classifier: Programming Language :: Python :: 3
Classifier: Programming Language :: Python :: 3.8
Classifier: Programming Language :: Python :: 3.9
Classifier: Programming Language :: Python :: 3.10
Classifier: Programming Language :: Python :: 3.11
Classifier: Programming Language :: Python :: 3.12
Classifier: Topic :: Internet :: WWW/HTTP
Classifier: Topic :: System :: Monitoring
Requires-Python: >=3.8
License-File: LICENSE
Requires-Dist: jsonschema[format]>=4.21.0
Requires-Dist: python-slugify
Provides-Extra: monitoring
Requires-Dist: Jinja2; extra == "monitoring"
Requires-Dist: boto; extra == "monitoring"
Requires-Dist: boto3; extra == "monitoring"
Requires-Dist: itemadapter; extra == "monitoring"
Requires-Dist: premailer; extra == "monitoring"
Requires-Dist: requests; extra == "monitoring"
Requires-Dist: scrapinghub; extra == "monitoring"
Requires-Dist: scrapinghub-entrypoint-scrapy; extra == "monitoring"
Requires-Dist: scrapy; extra == "monitoring"
Requires-Dist: sentry_sdk; extra == "monitoring"
Requires-Dist: slack_sdk; extra == "monitoring"
Dynamic: author
Dynamic: author-email
Dynamic: classifier
Dynamic: description
Dynamic: description-content-type
Dynamic: home-page
Dynamic: license
Dynamic: license-file
Dynamic: project-url
Dynamic: provides-extra
Dynamic: requires-dist
Dynamic: requires-python
Dynamic: summary
